libtwitter/__init__.py
libtwitter/libtwitter.py
libtwitter-0.0.7.dist-info/LICENSE
libtwitter-0.0.7.dist-info/METADATA
libtwitter-0.0.7.dist-info/WHEEL
libtwitter-0.0.7.dist-info/top_level.txt
libtwitter-0.0.7.dist-info/RECORD
