Metadata-Version: 2.1
Name: libtwitter
Version: 0.0.7
Summary: Pacote para pesquisar e processar tweets
Home-page: https://github.com/bianca-01/libtwitter
Author: Bianca Soares, Joanny Pacheco
Author-email: biancasousa439@gmail.com
License: UNKNOWN
Platform: UNKNOWN
Classifier: Programming Language :: Python :: 3
Classifier: License :: OSI Approved :: MIT License
Classifier: Operating System :: OS Independent
Requires-Python: >=3.8
License-File: LICENSE
Requires-Dist: oauth2
Requires-Dist: pandas (>=1.3.0)
Requires-Dist: wordcloud (>=1.8.1)
Requires-Dist: matplotlib (>=3.4.2)
